intermod_library/__init__.py
intermod_library/intermod_library.py
intermod_library-0.8.0.dist-info/LICENSE
intermod_library-0.8.0.dist-info/METADATA
intermod_library-0.8.0.dist-info/WHEEL
intermod_library-0.8.0.dist-info/RECORD
