Metadata-Version: 2.1
Name: intermod-library
Version: 0.8.0
Summary: Tools for calculating and viewing intermodulation products and harmonics.
Home-page: https://wboxx1.github.io/intermod-library
License: GPL-3.0
Author: Will Boxx
Author-email: wboxx1@gmail.com
Requires-Python: >=3.8
Classifier: License :: OSI Approved :: GNU General Public License v3 (GPLv3)
Classifier: Programming Language :: Python :: 3
Classifier: Programming Language :: Python :: 3.8
Classifier: Programming Language :: Python :: 3.9
Classifier: Programming Language :: Python :: 3.10
Classifier: Programming Language :: Python :: 3.11
Requires-Dist: matplotlib (>=3.0)
Requires-Dist: numba
Requires-Dist: numpy (>=1.16.5)
Requires-Dist: pandas (>=1.4.1)
Requires-Dist: scipy (>=1.8)
Project-URL: Repository, https://github.com/wboxx1/intermod-library
